permabots/__init__.py
permabots/admin.py
permabots/apps.py
permabots/caching.py
permabots/signals.py
permabots/tasks.py
permabots/urls_api.py
permabots/urls_processing.py
permabots/utils.py
permabots/validators.py
permabots/migrations/0001_initial.py
permabots/migrations/0002_auto_20160414_1051.py
permabots/migrations/0003_auto_20160420_0401.py
permabots/migrations/0004_auto_20160427_0856.py
permabots/migrations/0005_auto_20160428_0510.py
permabots/migrations/0006_auto_20160505_0352.py
permabots/migrations/0007_auto_20160530_0455.py
permabots/migrations/__init__.py
permabots/models/__init__.py
permabots/models/base.py
permabots/models/bot.py
permabots/models/environment_vars.py
permabots/models/handler.py
permabots/models/hook.py
permabots/models/kik_api.py
permabots/models/messenger_api.py
permabots/models/response.py
permabots/models/state.py
permabots/models/telegram_api.py
permabots/serializers/__init__.py
permabots/serializers/bot.py
permabots/serializers/environment_vars.py
permabots/serializers/handler.py
permabots/serializers/hook.py
permabots/serializers/kik_api.py
permabots/serializers/response.py
permabots/serializers/state.py
permabots/serializers/telegram_api.py
permabots/test/__init__.py
permabots/test/testcases.py
permabots/test/factories/__init__.py
permabots/test/factories/bot.py
permabots/test/factories/handler.py
permabots/test/factories/hook.py
permabots/test/factories/kik_api.py
permabots/test/factories/kik_lib.py
permabots/test/factories/messenger_api.py
permabots/test/factories/messenger_lib.py
permabots/test/factories/response.py
permabots/test/factories/state.py
permabots/test/factories/telegram_api.py
permabots/test/factories/telegram_lib.py
permabots/test/factories/user.py
permabots/views/__init__.py
permabots/views/api/__init__.py
permabots/views/api/base.py
permabots/views/api/bot.py
permabots/views/api/environment_vars.py
permabots/views/api/handler.py
permabots-2.2.3.dist-info/DESCRIPTION.rst
permabots-2.2.3.dist-info/METADATA
permabots-2.2.3.dist-info/RECORD
permabots-2.2.3.dist-info/WHEEL
permabots-2.2.3.dist-info/metadata.json
permabots-2.2.3.dist-info/top_level.txt
