Metadata-Version: 2.0
Name: permabots
Version: 2.2.3
Summary: Connect chats bots to your API apps
Home-page: https://github.com/jlmadurga/permabots
Author: Juan Madurga
Author-email: jlmadurga@gmail.com
License: BSD
Keywords: permabots
Platform: UNKNOWN
Classifier: Development Status :: 3 - Alpha
Classifier: Framework :: Django
Classifier: Framework :: Django :: 1.8
Classifier: Framework :: Django :: 1.9
Classifier: Intended Audience :: Developers
Classifier: License :: OSI Approved :: BSD License
Classifier: Natural Language :: English
Classifier: Programming Language :: Python :: 2
Classifier: Programming Language :: Python :: 2.7
Classifier: Programming Language :: Python :: 3
Classifier: Programming Language :: Python :: 3.3
Classifier: Programming Language :: Python :: 3.4
Classifier: Programming Language :: Python :: 3.5
Requires-Dist: Jinja2 (==2.8)
Requires-Dist: celery (==3.1.23)
Requires-Dist: django (>=1.9.1)
Requires-Dist: djangorestframework (==3.3.3)
Requires-Dist: jinja2-time (==0.1.0)
Requires-Dist: kik (==1.0.7)
Requires-Dist: messengerbot (==0.1.4)
Requires-Dist: python-telegram-bot (==4.2.0)
Requires-Dist: requests (==2.10.0)
Requires-Dist: shortuuid (==0.4.3)
